zzx_deep_genome/Standardization.py
zzx_deep_genome/__init__.py
zzx_deep_genome/cnn_tf_motif_1d.py
zzx_deep_genome/cnn_torch_motif_1d.py
zzx_deep_genome/filter_initialization.py
zzx_deep_genome/get_dataset.py
zzx_deep_genome/get_meme_file.py
zzx_deep_genome/get_pwm.py
zzx_deep_genome/tf_model.py
zzx_deep_genome/torch_model.py
zzx_deep_genome-0.1.5.dist-info/LICENSE.txt
zzx_deep_genome-0.1.5.dist-info/METADATA
zzx_deep_genome-0.1.5.dist-info/WHEEL
zzx_deep_genome-0.1.5.dist-info/top_level.txt
zzx_deep_genome-0.1.5.dist-info/RECORD
